Workbook

Sheet PARAMS
A1: Paramètre | B1: Valeur
A2: Taux horaire (€/h) | B2: 55
A3: Frais généraux % | B3: 0.1
A4: Marge aménagement % | B4: 0.1
A5: Marge vente % | B5: 0.15
A6: TVA % | B6: 0.21

Sheet PR_MATIERE
A1: N° poste | B1: Poste | C1: Texte | D1: Désignation (matière) | E1: Unité | F1: Qté poste | G1: Perte % | H1: PU net | I1: Total matière (poste) | J1: PU revient (poste) | K1: Marge aménagement % | L1: Marge vente % | M1: Total ligne (vente)
I2: =IFERROR(F2*H2*(1+G2),"") | J2: =IFERROR(I2/F2,"") | K2: =PARAMS!$B$4 | L2: =PARAMS!$B$5 | M2: =IFERROR(J2*F2*(1+K2)*(1+L2),"")
I3: =IFERROR(F3*H3*(1+G3),"") | J3: =IFERROR(I3/F3,"") | K3: =PARAMS!$B$4 | L3: =PARAMS!$B$5 | M3: =IFERROR(J3*F3*(1+K3)*(1+L3),"")
I4: =IFERROR(F4*H4*(1+G4),"") | J4: =IFERROR(I4/F4,"") | K4: =PARAMS!$B$4 | L4: =PARAMS!$B$5 | M4: =IFERROR(J4*F4*(1+K4)*(1+L4),"")
I5: =IFERROR(F5*H5*(1+G5),"") | J5: =IFERROR(I5/F5,"") | K5: =PARAMS!$B$4 | L5: =PARAMS!$B$5 | M5: =IFERROR(J5*F5*(1+K5)*(1+L5),"")
I6: =IFERROR(F6*H6*(1+G6),"") | J6: =IFERROR(I6/F6,"") | K6: =PARAMS!$B$4 | L6: =PARAMS!$B$5 | M6: =IFERROR(J6*F6*(1+K6)*(1+L6),"")
I7: =IFERROR(F7*H7*(1+G7),"") | J7: =IFERROR(I7/F7,"") | K7: =PARAMS!$B$4 | L7: =PARAMS!$B$5 | M7: =IFERROR(J7*F7*(1+K7)*(1+L7),"")
I8: =IFERROR(F8*H8*(1+G8),"") | J8: =IFERROR(I8/F8,"") | K8: =PARAMS!$B$4 | L8: =PARAMS!$B$5 | M8: =IFERROR(J8*F8*(1+K8)*(1+L8),"")
I9: =IFERROR(F9*H9*(1+G9),"") | J9: =IFERROR(I9/F9,"") | K9: =PARAMS!$B$4 | L9: =PARAMS!$B$5 | M9: =IFERROR(J9*F9*(1+K9)*(1+L9),"")
I10: =IFERROR(F10*H10*(1+G10),"") | J10: =IFERROR(I10/F10,"") | K10: =PARAMS!$B$4 | L10: =PARAMS!$B$5 | M10: =IFERROR(J10*F10*(1+K10)*(1+L10),"")
I11: =IFERROR(F11*H11*(1+G11),"") | J11: =IFERROR(I11/F11,"") | K11: =PARAMS!$B$4 | L11: =PARAMS!$B$5 | M11: =IFERROR(J11*F11*(1+K11)*(1+L11),"")

Sheet PR_MO
A1: N° poste | B1: Poste | C1: Texte | D1: Désignation (MO) | E1: Nb hommes | F1: Heures / homme / jour | G1: Délai (jours) | H1: Total heures (poste) | I1: Taux horaire | J1: Coût MO (poste) | K1: Marge aménagement % | L1: Marge vente % | M1: Total ligne (vente)
H2: =IFERROR(E2*F2*G2,"") | I2: =PARAMS!$B$2 | J2: =IFERROR(H2*I2,"") | K2: =PARAMS!$B$4 | L2: =PARAMS!$B$5 | M2: =IFERROR(J2*(1+K2)*(1+L2),"")
H3: =IFERROR(E3*F3*G3,"") | I3: =PARAMS!$B$2 | J3: =IFERROR(H3*I3,"") | K3: =PARAMS!$B$4 | L3: =PARAMS!$B$5 | M3: =IFERROR(J3*(1+K3)*(1+L3),"")
H4: =IFERROR(E4*F4*G4,"") | I4: =PARAMS!$B$2 | J4: =IFERROR(H4*I4,"") | K4: =PARAMS!$B$4 | L4: =PARAMS!$B$5 | M4: =IFERROR(J4*(1+K4)*(1+L4),"")
H5: =IFERROR(E5*F5*G5,"") | I5: =PARAMS!$B$2 | J5: =IFERROR(H5*I5,"") | K5: =PARAMS!$B$4 | L5: =PARAMS!$B$5 | M5: =IFERROR(J5*(1+K5)*(1+L5),"")
H6: =IFERROR(E6*F6*G6,"") | I6: =PARAMS!$B$2 | J6: =IFERROR(H6*I6,"") | K6: =PARAMS!$B$4 | L6: =PARAMS!$B$5 | M6: =IFERROR(J6*(1+K6)*(1+L6),"")
H7: =IFERROR(E7*F7*G7,"") | I7: =PARAMS!$B$2 | J7: =IFERROR(H7*I7,"") | K7: =PARAMS!$B$4 | L7: =PARAMS!$B$5 | M7: =IFERROR(J7*(1+K7)*(1+L7),"")
H8: =IFERROR(E8*F8*G8,"") | I8: =PARAMS!$B$2 | J8: =IFERROR(H8*I8,"") | K8: =PARAMS!$B$4 | L8: =PARAMS!$B$5 | M8: =IFERROR(J8*(1+K8)*(1+L8),"")
H9: =IFERROR(E9*F9*G9,"") | I9: =PARAMS!$B$2 | J9: =IFERROR(H9*I9,"") | K9: =PARAMS!$B$4 | L9: =PARAMS!$B$5 | M9: =IFERROR(J9*(1+K9)*(1+L9),"")
H10: =IFERROR(E10*F10*G10,"") | I10: =PARAMS!$B$2 | J10: =IFERROR(H10*I10,"") | K10: =PARAMS!$B$4 | L10: =PARAMS!$B$5 | M10: =IFERROR(J10*(1+K10)*(1+L10),"")
H11: =IFERROR(E11*F11*G11,"") | I11: =PARAMS!$B$2 | J11: =IFERROR(H11*I11,"") | K11: =PARAMS!$B$4 | L11: =PARAMS!$B$5 | M11: =IFERROR(J11*(1+K11)*(1+L11),"")

Sheet EXECUTION
A1: N° poste | B1: Poste | C1: Heures réelles (poste) | D1: Taux horaire réel | E1: Coût MO réel (poste) | F1: Coût matière réel (poste) | G1: Coût réel total (poste) | H1: Coût prévu total (poste) | I1: Écart € (réel - prévu) | J1: Écart % (réel - prévu)
D2: =PARAMS!$B$2 | E2: =IFERROR(C2*D2,"") | G2: =IFERROR(E2+F2,"") | H2: =IFERROR(SUMIF(PR_MATIERE!$A:$A,$A2,PR_MATIERE!$I:$I)+SUMIF(PR_MO!$A:$A,$A2,PR_MO!$J:$J),0) | I2: =IFERROR(G2-H2,"") | J2: =IFERROR(I2/H2,"")
D3: =PARAMS!$B$2 | E3: =IFERROR(C3*D3,"") | G3: =IFERROR(E3+F3,"") | H3: =IFERROR(SUMIF(PR_MATIERE!$A:$A,$A3,PR_MATIERE!$I:$I)+SUMIF(PR_MO!$A:$A,$A3,PR_MO!$J:$J),0) | I3: =IFERROR(G3-H3,"") | J3: =IFERROR(I3/H3,"")
D4: =PARAMS!$B$2 | E4: =IFERROR(C4*D4,"") | G4: =IFERROR(E4+F4,"") | H4: =IFERROR(SUMIF(PR_MATIERE!$A:$A,$A4,PR_MATIERE!$I:$I)+SUMIF(PR_MO!$A:$A,$A4,PR_MO!$J:$J),0) | I4: =IFERROR(G4-H4,"") | J4: =IFERROR(I4/H4,"")
D5: =PARAMS!$B$2 | E5: =IFERROR(C5*D5,"") | G5: =IFERROR(E5+F5,"") | H5: =IFERROR(SUMIF(PR_MATIERE!$A:$A,$A5,PR_MATIERE!$I:$I)+SUMIF(PR_MO!$A:$A,$A5,PR_MO!$J:$J),0) | I5: =IFERROR(G5-H5,"") | J5: =IFERROR(I5/H5,"")
D6: =PARAMS!$B$2 | E6: =IFERROR(C6*D6,"") | G6: =IFERROR(E6+F6,"") | H6: =IFERROR(SUMIF(PR_MATIERE!$A:$A,$A6,PR_MATIERE!$I:$I)+SUMIF(PR_MO!$A:$A,$A6,PR_MO!$J:$J),0) | I6: =IFERROR(G6-H6,"") | J6: =IFERROR(I6/H6,"")
D7: =PARAMS!$B$2 | E7: =IFERROR(C7*D7,"") | G7: =IFERROR(E7+F7,"") | H7: =IFERROR(SUMIF(PR_MATIERE!$A:$A,$A7,PR_MATIERE!$I:$I)+SUMIF(PR_MO!$A:$A,$A7,PR_MO!$J:$J),0) | I7: =IFERROR(G7-H7,"") | J7: =IFERROR(I7/H7,"")
D8: =PARAMS!$B$2 | E8: =IFERROR(C8*D8,"") | G8: =IFERROR(E8+F8,"") | H8: =IFERROR(SUMIF(PR_MATIERE!$A:$A,$A8,PR_MATIERE!$I:$I)+SUMIF(PR_MO!$A:$A,$A8,PR_MO!$J:$J),0) | I8: =IFERROR(G8-H8,"") | J8: =IFERROR(I8/H8,"")
D9: =PARAMS!$B$2 | E9: =IFERROR(C9*D9,"") | G9: =IFERROR(E9+F9,"") | H9: =IFERROR(SUMIF(PR_MATIERE!$A:$A,$A9,PR_MATIERE!$I:$I)+SUMIF(PR_MO!$A:$A,$A9,PR_MO!$J:$J),0) | I9: =IFERROR(G9-H9,"") | J9: =IFERROR(I9/H9,"")
D10: =PARAMS!$B$2 | E10: =IFERROR(C10*D10,"") | G10: =IFERROR(E10+F10,"") | H10: =IFERROR(SUMIF(PR_MATIERE!$A:$A,$A10,PR_MATIERE!$I:$I)+SUMIF(PR_MO!$A:$A,$A10,PR_MO!$J:$J),0) | I10: =IFERROR(G10-H10,"") | J10: =IFERROR(I10/H10,"")
D11: =PARAMS!$B$2 | E11: =IFERROR(C11*D11,"") | G11: =IFERROR(E11+F11,"") | H11: =IFERROR(SUMIF(PR_MATIERE!$A:$A,$A11,PR_MATIERE!$I:$I)+SUMIF(PR_MO!$A:$A,$A11,PR_MO!$J:$J),0) | I11: =IFERROR(G11-H11,"") | J11: =IFERROR(I11/H11,"")

Sheet SYNTHESE
A1: Élément | B1: Valeur
A2: Total matière (prévu) | B2: =IFERROR(SUM(PR_MATIERE!I2:I11),0)
A3: Total MO (prévu) | B3: =IFERROR(SUM(PR_MO!J2:J11),0)
A4: Coût direct prévu | B4: =IFERROR(B2+B3,0)
A5: Frais généraux (prévu) | B5: =IFERROR(B4*PARAMS!$B$3,0)
A6: PRIX DE REVIENT TOTAL (prévu) | B6: =IFERROR(B4+B5,0)
A8: Total vente (matière) | B8: =IFERROR(SUM(PR_MATIERE!M2:M11),0)
A9: Total vente (MO) | B9: =IFERROR(SUM(PR_MO!M2:M11),0)
A10: PRIX DE VENTE TOTAL HT | B10: =IFERROR(B8+B9,0)
A11: TVA % | B11: =PARAMS!$B$6
A12: PRIX DE VENTE TOTAL TTC | B12: =IFERROR(B10*(1+B11),0)

Sheet SOUMISSION
A1: Numéro | B1: Chantier | C1: Client | D1: Date | E1: PRIX DE REVIENT TOTAL | F1: PRIX DE VENTE HT | G1: TVA % | H1: PRIX TTC | I1: Remarques
A2: DEVIS-TEST | B2: À compléter | C2: À compléter | D2: 2026-01-22 | E2: =SYNTHESE!B6 | F2: =SYNTHESE!B10 | G2: =PARAMS!$B$6 | H2: =SYNTHESE!B12
