Workbook

Sheet COMPACT
A1: Article SCS | B1: Bordereau original ou reçu | E1: Désignation prix de revient matière | I1: Prix de revient unitaire
B2: Texte | C2: Désignation | D2: Quantité métrée détaillé | E2: texte | F2: Unité | G2: Qté poste | H2: Perte % sur conditionnement | I2: Total matière (poste) | J2: PU net | K2: PU Revient (poste) | L2: Marge % aménagement de chantier | M2: Marge vente % | N2: Total ligne
A3: 3.01 | E3: Transport | F3: =SIERREUR(INDEX(DATA!$E:$E;EQUIV("3.01|MAT|Transport";DATA!$A:$A;0));"") | G3: =SIERREUR(INDEX(DATA!$F:$F;EQUIV("3.01|MAT|Transport";DATA!$A:$A;0));"") | H3: =SIERREUR(INDEX(DATA!$G:$G;EQUIV("3.01|MAT|Transport";DATA!$A:$A;0));"") | I3: =SIERREUR(INDEX(DATA!$O:$O;EQUIV("3.01|MAT|Transport";DATA!$A:$A;0));"") | J3: =SIERREUR(INDEX(DATA!$H:$H;EQUIV("3.01|MAT|Transport";DATA!$A:$A;0));"") | K3: =SIERREUR(INDEX(DATA!$S:$S;EQUIV("3.01|MAT|Transport";DATA!$A:$A;0));"") | L3: =SIERREUR(INDEX(DATA!$M:$M;EQUIV("3.01|MAT|Transport";DATA!$A:$A;0));"") | M3: =SIERREUR(INDEX(DATA!$N:$N;EQUIV("3.01|MAT|Transport";DATA!$A:$A;0));"") | N3: =SIERREUR(INDEX(DATA!$T:$T;EQUIV("3.01|MAT|Transport";DATA!$A:$A;0));"")
E4: Petit matériel | F4: =SIERREUR(INDEX(DATA!$E:$E;EQUIV("3.01|MAT|Petit matériel";DATA!$A:$A;0));"") | G4: =SIERREUR(INDEX(DATA!$F:$F;EQUIV("3.01|MAT|Petit matériel";DATA!$A:$A;0));"") | H4: =SIERREUR(INDEX(DATA!$G:$G;EQUIV("3.01|MAT|Petit matériel";DATA!$A:$A;0));"") | I4: =SIERREUR(INDEX(DATA!$O:$O;EQUIV("3.01|MAT|Petit matériel";DATA!$A:$A;0));"") | J4: =SIERREUR(INDEX(DATA!$H:$H;EQUIV("3.01|MAT|Petit matériel";DATA!$A:$A;0));"") | K4: =SIERREUR(INDEX(DATA!$S:$S;EQUIV("3.01|MAT|Petit matériel";DATA!$A:$A;0));"") | L4: =SIERREUR(INDEX(DATA!$M:$M;EQUIV("3.01|MAT|Petit matériel";DATA!$A:$A;0));"") | M4: =SIERREUR(INDEX(DATA!$N:$N;EQUIV("3.01|MAT|Petit matériel";DATA!$A:$A;0));"") | N4: =SIERREUR(INDEX(DATA!$T:$T;EQUIV("3.01|MAT|Petit matériel";DATA!$A:$A;0));"")
E5: Briques | F5: =SIERREUR(INDEX(DATA!$E:$E;EQUIV("3.01|MAT|Briques";DATA!$A:$A;0));"") | G5: =SIERREUR(INDEX(DATA!$F:$F;EQUIV("3.01|MAT|Briques";DATA!$A:$A;0));"") | H5: =SIERREUR(INDEX(DATA!$G:$G;EQUIV("3.01|MAT|Briques";DATA!$A:$A;0));"") | I5: =SIERREUR(INDEX(DATA!$O:$O;EQUIV("3.01|MAT|Briques";DATA!$A:$A;0));"") | J5: =SIERREUR(INDEX(DATA!$H:$H;EQUIV("3.01|MAT|Briques";DATA!$A:$A;0));"") | K5: =SIERREUR(INDEX(DATA!$S:$S;EQUIV("3.01|MAT|Briques";DATA!$A:$A;0));"") | L5: =SIERREUR(INDEX(DATA!$M:$M;EQUIV("3.01|MAT|Briques";DATA!$A:$A;0));"") | M5: =SIERREUR(INDEX(DATA!$N:$N;EQUIV("3.01|MAT|Briques";DATA!$A:$A;0));"") | N5: =SIERREUR(INDEX(DATA!$T:$T;EQUIV("3.01|MAT|Briques";DATA!$A:$A;0));"")
E6: pierres | F6: =SIERREUR(INDEX(DATA!$E:$E;EQUIV("3.01|MAT|pierres";DATA!$A:$A;0));"") | G6: =SIERREUR(INDEX(DATA!$F:$F;EQUIV("3.01|MAT|pierres";DATA!$A:$A;0));"") | H6: =SIERREUR(INDEX(DATA!$G:$G;EQUIV("3.01|MAT|pierres";DATA!$A:$A;0));"") | I6: =SIERREUR(INDEX(DATA!$O:$O;EQUIV("3.01|MAT|pierres";DATA!$A:$A;0));"") | J6: =SIERREUR(INDEX(DATA!$H:$H;EQUIV("3.01|MAT|pierres";DATA!$A:$A;0));"") | K6: =SIERREUR(INDEX(DATA!$S:$S;EQUIV("3.01|MAT|pierres";DATA!$A:$A;0));"") | L6: =SIERREUR(INDEX(DATA!$M:$M;EQUIV("3.01|MAT|pierres";DATA!$A:$A;0));"") | M6: =SIERREUR(INDEX(DATA!$N:$N;EQUIV("3.01|MAT|pierres";DATA!$A:$A;0));"") | N6: =SIERREUR(INDEX(DATA!$T:$T;EQUIV("3.01|MAT|pierres";DATA!$A:$A;0));"")
E7: Désignation prix de revient main d’œuvre | F7: Nb hommes | G7: Heures hommes jour | H7: Total Heures (poste) | I7: Délai (jours) | J7: Taux horaire | K7: Coût MO (poste) | L7: Marge % aménagement de chantier | M7: Marge vente % | N7: Total ligne
E8: Piquage de briques 50 pcs homme jour | F8: =SIERREUR(INDEX(DATA!$I:$I;EQUIV("3.01|MO|Piquage de briques 50 pcs homme jour";DATA!$A:$A;0));"") | G8: =SIERREUR(INDEX(DATA!$J:$J;EQUIV("3.01|MO|Piquage de briques 50 pcs homme jour";DATA!$A:$A;0));"") | H8: =SIERREUR(INDEX(DATA!$P:$P;EQUIV("3.01|MO|Piquage de briques 50 pcs homme jour";DATA!$A:$A;0));"") | I8: =SIERREUR(INDEX(DATA!$K:$K;EQUIV("3.01|MO|Piquage de briques 50 pcs homme jour";DATA!$A:$A;0));"") | J8: =SIERREUR(INDEX(DATA!$L:$L;EQUIV("3.01|MO|Piquage de briques 50 pcs homme jour";DATA!$A:$A;0));"") | K8: =SIERREUR(INDEX(DATA!$Q:$Q;EQUIV("3.01|MO|Piquage de briques 50 pcs homme jour";DATA!$A:$A;0));"") | L8: =SIERREUR(INDEX(DATA!$M:$M;EQUIV("3.01|MO|Piquage de briques 50 pcs homme jour";DATA!$A:$A;0));"") | M8: =SIERREUR(INDEX(DATA!$N:$N;EQUIV("3.01|MO|Piquage de briques 50 pcs homme jour";DATA!$A:$A;0));"") | N8: =SIERREUR(INDEX(DATA!$T:$T;EQUIV("3.01|MO|Piquage de briques 50 pcs homme jour";DATA!$A:$A;0));"")
E9: Maçonnerie briques 03 m3 homme jour | F9: =SIERREUR(INDEX(DATA!$I:$I;EQUIV("3.01|MO|Maçonnerie briques 03 m3 homme jour";DATA!$A:$A;0));"") | G9: =SIERREUR(INDEX(DATA!$J:$J;EQUIV("3.01|MO|Maçonnerie briques 03 m3 homme jour";DATA!$A:$A;0));"") | H9: =SIERREUR(INDEX(DATA!$P:$P;EQUIV("3.01|MO|Maçonnerie briques 03 m3 homme jour";DATA!$A:$A;0));"") | I9: =SIERREUR(INDEX(DATA!$K:$K;EQUIV("3.01|MO|Maçonnerie briques 03 m3 homme jour";DATA!$A:$A;0));"") | J9: =SIERREUR(INDEX(DATA!$L:$L;EQUIV("3.01|MO|Maçonnerie briques 03 m3 homme jour";DATA!$A:$A;0));"") | K9: =SIERREUR(INDEX(DATA!$Q:$Q;EQUIV("3.01|MO|Maçonnerie briques 03 m3 homme jour";DATA!$A:$A;0));"") | L9: =SIERREUR(INDEX(DATA!$M:$M;EQUIV("3.01|MO|Maçonnerie briques 03 m3 homme jour";DATA!$A:$A;0));"") | M9: =SIERREUR(INDEX(DATA!$N:$N;EQUIV("3.01|MO|Maçonnerie briques 03 m3 homme jour";DATA!$A:$A;0));"") | N9: =SIERREUR(INDEX(DATA!$T:$T;EQUIV("3.01|MO|Maçonnerie briques 03 m3 homme jour";DATA!$A:$A;0));"")
E10: Maçonnerie pierres 02 m3 homme jour | F10: =SIERREUR(INDEX(DATA!$I:$I;EQUIV("3.01|MO|Maçonnerie pierres 02 m3 homme jour";DATA!$A:$A;0));"") | G10: =SIERREUR(INDEX(DATA!$J:$J;EQUIV("3.01|MO|Maçonnerie pierres 02 m3 homme jour";DATA!$A:$A;0));"") | H10: =SIERREUR(INDEX(DATA!$P:$P;EQUIV("3.01|MO|Maçonnerie pierres 02 m3 homme jour";DATA!$A:$A;0));"") | I10: =SIERREUR(INDEX(DATA!$K:$K;EQUIV("3.01|MO|Maçonnerie pierres 02 m3 homme jour";DATA!$A:$A;0));"") | J10: =SIERREUR(INDEX(DATA!$L:$L;EQUIV("3.01|MO|Maçonnerie pierres 02 m3 homme jour";DATA!$A:$A;0));"") | K10: =SIERREUR(INDEX(DATA!$Q:$Q;EQUIV("3.01|MO|Maçonnerie pierres 02 m3 homme jour";DATA!$A:$A;0));"") | L10: =SIERREUR(INDEX(DATA!$M:$M;EQUIV("3.01|MO|Maçonnerie pierres 02 m3 homme jour";DATA!$A:$A;0));"") | M10: =SIERREUR(INDEX(DATA!$N:$N;EQUIV("3.01|MO|Maçonnerie pierres 02 m3 homme jour";DATA!$A:$A;0));"") | N10: =SIERREUR(INDEX(DATA!$T:$T;EQUIV("3.01|MO|Maçonnerie pierres 02 m3 homme jour";DATA!$A:$A;0));"")
E11: Démolition 1 m3 homme jour | F11: =SIERREUR(INDEX(DATA!$I:$I;EQUIV("3.01|MO|Démolition 1 m3 homme jour";DATA!$A:$A;0));"") | G11: =SIERREUR(INDEX(DATA!$J:$J;EQUIV("3.01|MO|Démolition 1 m3 homme jour";DATA!$A:$A;0));"") | H11: =SIERREUR(INDEX(DATA!$P:$P;EQUIV("3.01|MO|Démolition 1 m3 homme jour";DATA!$A:$A;0));"") | I11: =SIERREUR(INDEX(DATA!$K:$K;EQUIV("3.01|MO|Démolition 1 m3 homme jour";DATA!$A:$A;0));"") | J11: =SIERREUR(INDEX(DATA!$L:$L;EQUIV("3.01|MO|Démolition 1 m3 homme jour";DATA!$A:$A;0));"") | K11: =SIERREUR(INDEX(DATA!$Q:$Q;EQUIV("3.01|MO|Démolition 1 m3 homme jour";DATA!$A:$A;0));"") | L11: =SIERREUR(INDEX(DATA!$M:$M;EQUIV("3.01|MO|Démolition 1 m3 homme jour";DATA!$A:$A;0));"") | M11: =SIERREUR(INDEX(DATA!$N:$N;EQUIV("3.01|MO|Démolition 1 m3 homme jour";DATA!$A:$A;0));"") | N11: =SIERREUR(INDEX(DATA!$T:$T;EQUIV("3.01|MO|Démolition 1 m3 homme jour";DATA!$A:$A;0));"")
G13: Heures réelles (poste) | I13: Rendement et résultat en exécution | L13: Coût matière réel (poste) | M13: Écart % (réel - prévu) | N13: Écart € (réel - prévu)

Sheet DATA
A1: Key | B1: Poste | C1: Type | D1: Sous-poste | E1: Unité | F1: Qté poste | G1: Perte | H1: PU net | I1: Nb hommes | J1: Heures hommes jour | K1: Délai (jours) | L1: Taux horaire | M1: Marge chantier | N1: Marge vente | O1: Total matière (poste) | P1: Total Heures (poste) | Q1: Coût MO (poste) | R1: Total Revient (poste) | S1: PU Revient (poste) | T1: Total ligne
A2: 3.01|MAT|Transport | B2: 3.01 | C2: Matière | D2: Transport | E2: forfait | F2: 1 | G2: 0 | H2: 100 | M2: 0 | N2: 0 | O2: =SI(F2=0;"";F2*H2*(1+G2)) | P2: 0 | Q2: 0 | R2: =SI(O2="";"";O2+Q2) | S2: =SI(F2=0;"";R2/F2) | T2: =SI(R2="";"";R2*(1+M2+N2))
A3: 3.01|MAT|Petit matériel | B3: 3.01 | C3: Matière | D3: Petit matériel | E3: forfait | F3: 1 | G3: 0 | H3: 50 | M3: 0 | N3: 0 | O3: =SI(F3=0;"";F3*H3*(1+G3)) | P3: 0 | Q3: 0 | R3: =SI(O3="";"";O3+Q3) | S3: =SI(F3=0;"";R3/F3) | T3: =SI(R3="";"";R3*(1+M3+N3))
A4: 3.01|MAT|Briques | B4: 3.01 | C4: Matière | D4: Briques | E4: m2 | F4: 10 | G4: 0.05 | H4: 12 | M4: 0 | N4: 0 | O4: =SI(F4=0;"";F4*H4*(1+G4)) | P4: 0 | Q4: 0 | R4: =SI(O4="";"";O4+Q4) | S4: =SI(F4=0;"";R4/F4) | T4: =SI(R4="";"";R4*(1+M4+N4))
A5: 3.01|MAT|pierres | B5: 3.01 | C5: Matière | D5: pierres | E5: m2 | F5: 10 | G5: 0.05 | H5: 20 | M5: 0 | N5: 0 | O5: =SI(F5=0;"";F5*H5*(1+G5)) | P5: 0 | Q5: 0 | R5: =SI(O5="";"";O5+Q5) | S5: =SI(F5=0;"";R5/F5) | T5: =SI(R5="";"";R5*(1+M5+N5))
A6: 3.01|MO|Piquage de briques 50 pcs homme jour | B6: 3.01 | C6: Main d’œuvre | D6: Piquage de briques 50 pcs homme jour | E6: h/homme | F6: 0 | G6: 0 | H6: 0 | I6: 2 | J6: 7 | K6: 1 | L6: 50 | M6: 0 | N6: 0 | O6: 0 | P6: =SI(I6=0;"";I6*J6*K6) | Q6: =SI(P6="";"";P6*L6) | R6: =SI(OU(O6="";Q6="");"";O6+Q6) | S6: =SI(R6="";"";R6) | T6: =SI(R6="";"";R6*(1+M6+N6))
A7: 3.01|MO|Maçonnerie briques 03 m3 homme jour | B7: 3.01 | C7: Main d’œuvre | D7: Maçonnerie briques 03 m3 homme jour | E7: h/homme | F7: 0 | G7: 0 | H7: 0 | I7: 3 | J7: 7 | K7: 1 | L7: 50 | M7: 0 | N7: 0 | O7: 0 | P7: =SI(I7=0;"";I7*J7*K7) | Q7: =SI(P7="";"";P7*L7) | R7: =SI(OU(O7="";Q7="");"";O7+Q7) | S7: =SI(R7="";"";R7) | T7: =SI(R7="";"";R7*(1+M7+N7))
A8: 3.01|MO|Maçonnerie pierres 02 m3 homme jour | B8: 3.01 | C8: Main d’œuvre | D8: Maçonnerie pierres 02 m3 homme jour | E8: h/homme | F8: 0 | G8: 0 | H8: 0 | I8: 2 | J8: 7 | K8: 1 | L8: 50 | M8: 0 | N8: 0 | O8: 0 | P8: =SI(I8=0;"";I8*J8*K8) | Q8: =SI(P8="";"";P8*L8) | R8: =SI(OU(O8="";Q8="");"";O8+Q8) | S8: =SI(R8="";"";R8) | T8: =SI(R8="";"";R8*(1+M8+N8))
A9: 3.01|MO|Démolition 1 m3 homme jour | B9: 3.01 | C9: Main d’œuvre | D9: Démolition 1 m3 homme jour | E9: h/homme | F9: 0 | G9: 0 | H9: 0 | I9: 1 | J9: 7 | K9: 1 | L9: 50 | M9: 0 | N9: 0 | O9: 0 | P9: =SI(I9=0;"";I9*J9*K9) | Q9: =SI(P9="";"";P9*L9) | R9: =SI(OU(O9="";Q9="");"";O9+Q9) | S9: =SI(R9="";"";R9) | T9: =SI(R9="";"";R9*(1+M9+N9))
